MANIFEST.in
README.rst
setup.py
epigenomic_dataset/__init__.py
epigenomic_dataset/__version__.py
epigenomic_dataset/build.py
epigenomic_dataset/concatenate.py
epigenomic_dataset/extract.py
epigenomic_dataset/load_epigenomes.py
epigenomic_dataset/load_tasks.py
epigenomic_dataset/logging.py
epigenomic_dataset/mine.py
epigenomic_dataset.egg-info/PKG-INFO
epigenomic_dataset.egg-info/SOURCES.txt
epigenomic_dataset.egg-info/dependency_links.txt
epigenomic_dataset.egg-info/requires.txt
epigenomic_dataset.egg-info/top_level.txt
epigenomic_dataset/utils/__init__.py
epigenomic_dataset/utils/available_metrics.py
epigenomic_dataset/utils/cell_lines.py
epigenomic_dataset/utils/normalize_epigenomic_data.py
epigenomic_dataset/utils/window_sizes.py