Metadata-Version: 2.1
Name: epigenomic-dataset
Version: 1.2.13
Summary: Python package wrapping ENCODE epigenomic data for a number of reference cell lines.
Home-page: https://github.com/LucaCappelletti94/epigenomic_dataset
Author: Luca Cappelletti
Author-email: cappelletti.luca94@gmail.com
License: MIT
Platform: UNKNOWN
Classifier: Development Status :: 3 - Alpha
Classifier: License :: OSI Approved :: MIT License
Classifier: Programming Language :: Python :: 3
Provides-Extra: test
